{
  "1.アイドル選択": "1. Pilih Idol",
  "2.サポート選択": "2. Pilih Support",
  "3.メモリー選択": "3. Pilih Memori",
  "3年1組の日常": "Harian Kelas 3-1",
  "4.開始確認": "4. Konfirm Mulai",
  "AP回復アイテム": "Item Pemulihan AP",
  "Da.が<color=#0A84F8>999</color>上昇した!": "Da. naik <color=#0A84F8>999</color>!",
  "Exchange 交換Pt Trade Pts to acquire a Produce Idol": "Tukar Pt untuk Produce Idol",
  "PERFECT上限UP": "Batas PERFECT UP",
  "PLv.5で解放": "Terbuka di PLv.5",
  "PLv10で解放": "Terbuka di PLv.10",
  "PLvアップ": "PLv Naik",
  "Pアイテムが選択されてません": "P-Item Belum Dipilih",
  "Pドリンク詳細": "P-Drink Detail",
  "Pドリンク／アイテム": "P-Drink/Item",
  "Pポイント不足": "P-Poin Kurang",
  "Pメニュー削除": "P-Menu Hapus",
  "Pメニュー名": "P-Menu Nama",
  "SR": "SR",
  "SR以上1枚確定": "Pasti 1 SR keatas",
  "SSR": "SSR",
  "TAPで次へ": "TAP untuk lanjut",
  "True Endボーナスは\n該当アイドルのすべてのプロデュースアイドルに反映されます": "Bonus True End akan diterapkan ke\nsemua Produce Idol dari idol tersebut",
  "True Endボーナスは含まれていません": "Bonus True End tidak termasuk",
  "TrueEndアチーブメント": "True End Achievement",
  "TrueEnd達成数": "Total True End",
  "Vi.が<color=#F7B12F>999</color>上昇した!": "Vi. naik <color=#F7B12F>999</color>!",
  "Vo.が<color=#F23584>999</color>上昇した!": "Vo. naik <color=#F23584>999</color>!",
  "[__split__]ひな祭り": "[__split__] Hinamatsuri",
  "[__split__]アニメイト": "[__split__] Animate",
  "[__split__]クリスマス": "[__split__] Christmas",
  "[__split__]ハロウィン": "[__split__] Halloween",
  "[__split__]バレンタイン": "[__split__] Valentine",
  "[__split__]夏": "[__split__] Musim Panas",
  "[__split__] 桜": "[__split__] Sakura",
  "[__split__] 祭": "[__split__] Festival",
  "[成長]": "[Growth]",
  "ptで解放": "Buka dengan pt",
  "※1日あたりの獲得上限は2000です": "※Batas harian maksimal 2000",
  "※スコアボーナスはサポートボーナスを含んだ値です": "※Skor bonus sudah termasuk bonus support",
  "※保存していない写真は削除されます": "※Foto yang tidak disimpan akan dihapus",
  "※後から他のアイドルもプロデュース可能です": "※Idol lain bisa di-produce nanti",
  "※挑戦回数は消費しません / レートptは獲得できません": "※Tiket tantangan tidak berkurang / Poin rate tidak didapat",
  "あさり先生のプロデュースゼミ": "Seminar Produksi Asari-Sensei",
  "あと1回": "Tinggal 1 kali",
  "あらすじ\n": "Ringkasan\n",
  "お": "Di",
  "お出かけ終了時、体力回復9": "Selesai Pergi, Pulihkan Stamina 9",
  "かわいく": "Imut",
  "が解放されました": "Telah Terbuka",
  "きらぼしステージ": "Panggung Kiraboshi",
  "ことねと麻央の日常": "Keseharian Kotone & Mao",
  "このアイドルでプロデュースを開始しますか？\n※後から他のアイドルもプロデュース可能です": "Mulai Produce idol ini?\n※Idol lain bisa di-produce nanti",
  "このフォトをアルバムに保存": "Simpan foto ke album",
  "これからが彼女たちのはじまり": "Inilah awal mula kisah mereka",
  "ご注意": "Perhatian",
  "ご迷惑をお掛け致しますが、\nご理解のほどよろしくお願いします": "Mohon maaf atas ketidaknyamanannya.\nTerima kasih atas pengertiannya.",
  "すべてのコミュを\n解放しました": "Semua Commu\ntelah terbuka",
  "すべてのコミュを\n開放しました": "Semua Commu\ntelah dibuka",
  "すべての報酬を\n獲得しました": "Semua hadiah\ntelah didapat",
  "ぜひ使ってみてくださいね！": "Ayo, cobain sekarang!",
  "その他のスキルカード": "Skill Card lainnya",
  "たけのこたけのこニョッキッキ！": "Takenoko Takenoko Nyokkikki!",
  "つまづいてなんて いられない": "Aku nggak boleh nyerah di sini",
  "では、この状態で\n体力消費の多いスキルカードを\n使ってみましょう": "Nah, dalam kondisi ini,\ncoba pakai Skill Card\nyang boros Stamina.",
  "で初星コミュ 第1章「第1話」解放": "Buka Hatsuboshi Commu Bab 1 \"Eps. 1\"",
  "で解放": "Buka dengan",
  "どやてんホール": "Doyaten Hall",
  "はつみちゃんコイン 獲得": "Koin Hatsumi-chan Didapat",
  "まいだおれスタジアム": "Maidaore Stadium",
  "まだスキルカードを選択することができますが\n本当にターンを終了しますか？\\n(体力が4回復します)": "Masih ada Skill Card yang bisa dipilih.\nYakin mau mengakhiri turn sekarang?\n(Stamina bakal pulih 4)",
  "まったり": "Santai",
  "みたことのある演出のスキップが設定できます\n※みたことのない演出の場合、ONになっていても\nスキップされません": "Kamu bisa mengatur skip untuk performa\nyang sudah pernah dilihat. Performa baru\ntidak akan di-skip meski pengaturan ON.",
  "もう一枚使用できます": "Bisa pakai 1 kartu lagi",
  "もしくはスコア1000以上": "Atau skor 1000 ke atas",
  "わきばら": "Pinggang",
  "アイテム/ドリンク名": "Nama Item/Minuman",
  "アイテム名": "Nama Item",
  "アイドルの親密度を２０まで上げる": "Naikkan Lv Bond Idol sampai 20",
  "アイドルアリーナ": "Idol Arena",
  "アイドル名": "Nama Idol",
  "アイドル科生徒": "Murid Jurusan Idol",
  "アイドル衣装：": "Kostum Idol: ",
  "アナザー名": "Nama Lain",
  "アニホール": "Ani Hall",
  "アノマリーガシャ（毎月1日 5時00分更新）": "Anomaly Gacha (Update setiap tanggal 1 pukul 05:00)",
  "アプリ専用通貨等の購入には、年齢別に限度額 yang 設定されています": "Ada batas pembelian mata uang aplikasi\nberdasarkan kategori usia.",
  "アルバムに保存済み": "Tersimpan di Album",
  "イチバンカワイイ": "Paling Imut",
  "イベントカフェ": "Event Kafe",
  "イベントコイン": "Koin Event",
  "イベントコインボーナス": "Bonus Koin Event",
  "イベント開催記念！APドリンクプレゼント": "Rayakan Event! Hadiah AP Drink untukmu",
  "インタビュー": "Wawancara",
  "エアロビクス": "Aerobik",
  "エナジー": "Energi",
  "エナジードリンク": "Minuman Energi",
  "オーディションを選択してください": "Silakan pilih audisi",
  "オーディションボーナス": "Bonus Audisi",
  "オーディション開始": "Mulai Audisi",
  "カスタマイズ確認": "Konfirm Kustomisasi",
  "カスタマイズ詳細": "Detail Kustomisasi",
  "カード名": "Nama Kartu",
  "ガシャへ": "Ke Gacha",
  "ガシャ回数： 1234回": "Jumlah Gacha: 1234 kali",
  "ガシャ回数：1回": "Jumlah Gacha: 1 kali",
  "ガシャ開催までもうしばらくお待ちください\nご協力のほどよろしくお願いいたします": "Mohon tunggu sebentar sampai Gacha dimulai\nTerima kasih atas kerja samanya",
  "ガシャ開催準備中": "Gacha Sedang Berlangsung",
  "キャッシュ\nクリア": "Hapus\nCache",
  "キャッチコピーをつける": "Tambahkan slogan",
  "キャラクター名": "Nama Karakter",
  "キャンプ場": "Area Perkemahan",
  "キャンペーン\nミッション": "Misi\nKampanye",
  "クラス対抗初星大運動会": "Fes Olahraga Hatsuboshi Antar Kelas",
  "クリアまであと": "Sisa sampai Clear",
  "クリア報酬": "Hadiah Clear",
  "クリア履歴": "Riwayat Clear",
  "グレード7以降解放": "Terbuka setelah Grade 7",
  "ゲームセールスランキング1位記念のプレゼントです": "Hadiah perayaan peringkat 1 dalam penjualan game.",
  "コインを消費して\\nボックスガシャを1回引きますか？": "Pakai Coin untuk\ntarik Box Gacha 1 kali?",
  "コインガシャを1,000回引こう": "Tarik Coin Gacha 1.000 kali",
  "コイン交換所": "Penukaran Coin",
  "コミュに登場するアイドルを選択する。": "Pilih idol yang akan muncul di Commu.",
  "コミュを見る": "Lihat Commu",
  "コンテストでスコアを24,000以上獲得しよう": "Raih 24.000 score atau lebih dalam kontes",
  "コンテストシーズン5開催中": "Kontes Musim 5 Sedang Berlangsung",
  "コンテスト未参加": "Belum Mengikuti Kontes",
  "コンテスト用Pアイテム": "P-Item Kontes",
  "コンテスト用スキルカード": "Skill Card Kontes",
  "コンテスト詳細": "Detail Kontes",
  "サポートカードをレンタルしたプロデューサーを\nフォローしますか？": "Ikuti Produser tempat Anda meminjam\nSupport Card?",
  "サポートカード名": "Nama Support Card",
  "サポート強化Pt2倍増加": "Poin Penguatan Support naik 2x Lipat",
  "サークル情報編集": "Ubah Info Circle",
  "サークル解散": "Bubarkan Circle",
  "シーズン終了時に獲得できる報酬です": "Hadiah yang didapat pada akhir musim",
  "ジュエル\nを購入しました": "Jewel\ntelah dibeli",
  "ジール": "Zeal",
  "ジールコインガシャ": "Zeal Coin Gacha",
  "ジールコインガシャリザルト": "Hasil Zeal Coin Gacha",
  "スイッチON": "Switch ON",
  "スカウト前": "Pre-Gacha",
  "スキルカードが選択されてません": "Skill Card belum dipilih",
  "スキルカードが除外に移動した時、体力回復": "Pulihkan stamina saat Skill Card dibuang",
  "スキルカードの消費体力が増加 ": "Konsumsi stamina Skill Card naik",
  "スキルカードの消費体力を減少": "Kurangi konsumsi stamina Skill Card ",
  "スキルカードの消費体力を減少 ": "Kurangi stamina Skill Card ",
  "スキルカードを使うごとに\n体力消費1がつきますが、\n1段階目よりも\nパラメータの上昇量がアップします": "Setiap menggunakan Skill Card akan mengonsumsi 1 stamina,\nnamun peningkatan parameter akan lebih besar\ndibandingkan tahap pertama.",
  "スキルカードを保留に\n移動することができましたね": "Kamu berhasil memindahkan Skill Card ke area hold.",
  "スキルカードを獲得する。獲得したスキルカードはレッスン終了時に削除される": "Dapatkan Skill Card. Skill Card yang didapat akan dihapus saat latihan berakhir.",
  "スキルカード・トラブルの一部効果の誤表記のお詫びです": "Mohon maaf atas kesalahan penulisan efek pada beberapa Skill Card Trouble.",
  "スキルカード名": "Nama Skill Card",
  "スキルカード強化時、ボーカル上昇+3": "Saat menaikkan Skill Card, Vocal +3",
  "スキルカード抽選可能回数：あと○回": "Sisa kesempatan tarik Skill Card: ○ kali",
  "スキルカード獲得": "Dapatkan Skill Card",
  "スコアが2400以上の場合スコア": "Jika Score 2400 atau lebih, tambah Score",
  "スコアが上昇しない": "Score tidak meningkat",
  "スコアを上昇させるスキルカード": "Skill Card peningkat Score",
  "スコアボーナスPt": "Poin Bonus Score",
  "スコアランクボーナスPt": "Poin Bonus Score Peringkat",
  "スコア上昇効果を主とするスキルカード": "Skill Card yang berfokus pada efek peningkatan Score",
  "スコア上昇量を": "Tingkatkan jumlah Score sebesar",
  "スコア上昇量を増加（○〆好印象による上昇も含む）": "Meningkatkan perolehan Score (termasuk bonus dari ○〆Good Impression)",
  "ステージ別\nランキング": "Peringkat\nsesuai stage",
  "ストアセールスランキング1位記念のプレゼントです": "Hadiah perayaan peringkat 1 dalam penjualan toko aplikasi.",
  "ストーリーイベントコミュ名": "Nama Commu Story Event",
  "ストーリーイベント無料解放期間": "Periode Terbuka Gratis Story Event",
  "ストーリーボックス": "Story Box",
  "ストーリーボックスガシャ確認": "Konfirmasi Gacha Story Box",
  "スパリゾート": "Spa Resort",
  "スリーサイズ": "Tiga Ukuran B.W.H",
  "セットアップ中…": "Sedang Menyiapkan...",
  "センスガシャ（毎月1日 5時00分更新）": "Sense Gacha (Update setiap tanggal 1 pukul 05:00)",
  "ソート名": "Urutan Nama",
  "タグ設定無し": "Tag tidak diatur",
  "タップで詳細を確認できます": "Ketuk untuk melihat detail",
  "タブ": "Tab",
  "タワー": "Tower",
  "ターン目": "Turn ke-",
  "ターン終了時残り2ターン以内の場合、スコア": "Jika sisa 2 Turn atau kurang saat Turn berakhir, tambah Score",
  "ダイヤの原石": "Intan yang Belum Diasah",
  "ダンス トレーナー": "Pelatih Dance",
  "チャレンジPアイテムは、アイドルごとに特定の条件を満たすことで最大3つ解放され、選択することができます。": "Challenge P-Item dapat terbuka hingga maksimal 3 untuk setiap idol dengan memenuhi kondisi tertentu, dan dapat dipilih.",
  "チャレンジPアイテムを設定した状態でプロデュースを開始すると、レッスン・SPレッスンのPERFECT上限があがります。": "Memulai Produce dengan memasang Challenge P-Item akan meningkatkan batas PERFECT untuk Lesson dan SP Lesson.",
  "テクニシャン\nスキルカードを合計2,000獲得": "Teknisi\nDapatkan total 2.000 Skill Card",
  "テンションとは": "Apa itu Tension",
  "トラやねんハウス": "Torayanen House",
  "ハイスコア": "High Score",
  "ハイスコア対象": "Target High Score",
  "バッチ獲得条件": "Syarat Mendapatkan Badge",
  "バフ": "Buff",
  "パス名": "Nama Pass",
  "パラメータが上昇しない": "Param tidak meningkat",
  "パラメータが上昇しましたね": "Param telah meningkat",
  "パラメータ・成長率ボーナスアップ": "Bonus tingkat param/pertumbuhan",
  "パラメータ上昇値を増加\nパラメータ上昇効果を持たないスキルカードには影響しない": "Meningkatkan nilai up param.\nTidak berpengaruh pada Skill Card yang tidak memiliki efek up param.",
  "パラメータ上昇効果を主とするスキルカード": "Skill Card yang berfokus pada efek peningkatan param",
  "パラメータ上昇回数を増加\nパラメータ上昇効果を持たないスキルカードには影響しない": "Meningkatkan jumlah up param.\nTidak berpengaruh pada Skill Card yang tidak memiliki efek up param.",
  "パラメータ上昇量を": "Jumlah up param sebesar",
  "パラメータ上昇量を増加": "Meningkatkan jumlah perolehan param",
  "ビジュアル トレーナー": "Pelatih Visual",
  "ピックアップ": "Pickup",
  "ピックアップ報酬は\nありません": "Tidak ada hadiah\nPick-Up",
  "ファン投票数不足": "Jumlah fan-votes tidak cukup",
  "フォロー確認": "Konfirm Ikuti",
  "フレンドガシャ（毎月1日 5時00分更新）": "Friend Gacha (Update setiap tanggal 1 pukul 05:00)",
  "プラチナガシャ": "Platinum Gacha",
  "プランが<color=#8581FF>ロジック</color>のアイドルをプロデュースしている場合のみ発動": "Aktif saat Produce idol dengan rencana <color=#8581FF>Logic</color>",
  "プランジールのアイドルを1回プロデュースしよう": "Produce idol dari rencana tipe Plangere sebanyak 1 kali",
  "プランタイプ": "Tipe Rencana",
  "プロデューサーLvが上がると新しいスキルカードや\nPドリンクなどが解放され、プロデュース中に登場します。": "Saat Producer Level meningkat, Skill Card baru,\nP-Drink, dan lainnya akan terbuka dan muncul saat melakukan Produce.",
  "プロデューサーレベルは最大です": "Producer Level telah mencapai maks",
  "プロデュース\n完了": "Produce\nSelesai",
  "プロデュースがんばりましょう！": "Ayo semangat lakukan Produce!",
  "プロデュースで獲得できるサポート強化Ptが増加します": "Poin Penguatan Support yang didapat saat Produce akan meningkat",
  "プロデュースのおでかけの選択肢の一部効果の誤表記のお詫びです": "Maaf atas kesalahan penulisan efek pada beberapa pilihan Jalan-jalan saat Produce.",
  "プロデュースのコツ": "Tips Produce",
  "プロデュースのレッスン・試験にて、特定条件でスキルカードが選択できなくなる現象のお詫びです": "Maaf atas kendala tidak bisa memilih Skill Card dalam kondisi tertentu saat Lesson dan Ujian Produce.",
  "プロデュースの評価に応じて\nメモリーの性能 platform 変化します。": "Performa Memory akan berubah sesuai\nevaluasi Produce yang didapat.",
  "プロデュースの試験に再挑戦できる": "Dapat mengulang kembali Ujian Produce",
  "プロデュースの追い込みレッスン後に特定の条件で通信エラーになる現象のお詫びです": "Maaf atas kendala galat komunikasi dalam kondisi tertentu setelah Lesson Akhir Produce.",
  "プロデュースを進めることでミッションが進行します\nサークルメンバーと協力して進めよう": "Selesaikan misi dengan terus melakukan Produce.\nAyo bekerja sama dengan anggota Circle!",
  "プロデュース中あと２回": "Tersisa 2x lagi selama Produce",
  "プロデュース報酬ではつみちゃんコインが獲得できるようになります": "Sekarang kamu bisa dapatkan koin Hatsumi-chan sebagai hadiah Produce!",
  "プロデュース評価": "Evaluasi Produce",
  "プロデュース開始時に使用するとサポート強化Ptの入手量が2倍になる獲得量上昇アイテム": "Item peningkatan perolehan yang melipatgandakan Poin Penguatan Support jika digunakan saat memulai Produce.",
  "プロデュース開始時に使用すると特訓アイテムの入手量が2倍になる獲得量上昇アイテム": "Item peningkatan perolehan yang melipatgandakan Item Latihan Khusus jika digunakan saat memulai Produce.",
  "ヘアスタイル": "Gaya Rambut",
  "ヘアスタイルと衣装を選択してください。": "Silakan pilih Gaya Rambut dan Kostum.",
  "ホームのコンテストから移動できます": "Dapat diakses melalui Kontes di halaman Utama",
  "ボックスガシャを100回引くと解放": "Terbuka setelah menarik Box Gacha sebanyak 100 kali",
  "ボーカルを育てよう": "Ayo tingkatkan Vocal",
  "ボーカルト レーナー": "Pelatih Vocal",
  "ボーナスはこちらで確認できます\nターンごとにボーナスが変わるので\n注意してくださいね！": "Bonus dapat diperiksa di sini.\nPerhatikan bahwa bonus akan berubah\ndi setiap Turn!",
  "マスター\nアチーブメント": "Master\nAchievement",
  "ミッションが進捗しました": "Misi telah mengalami kemajuan",
  "ミッションクリア": "Misi Selesai",
  "ミッションコンプリート": "Misi Sempurna",
  "ミッションシート\n": "Lembar Misi\n",
  "ミュージックへ": "Ke Musik",
  "メイン効果の名称": "Nama Efek Utama",
  "メニュー使用確認": "Konfirmasi Penggunaan Menu",
  "メモリーにするフォトを選んでください": "Silakan pilih foto untuk dijadikan Memory",
  "メモリーのレンタル回数が残っています\nレンタルメモリーを編成せず次へ進みますか？": "Masih ada kesempatan meminjam Memory.\nTetap lanjut tanpa memasukkan Rental Memory?",
  "メモリーを再生成できる回数が2回に増加します": "Jumlah kesempatan pembuatan ulang Memory meningkat menjadi 2 kali",
  "メモリーを所持していません": "Tidak memiliki Memory",
  "メモリーレンタル回数2倍増加": "Peningkatan jumlah peminjaman Memory 2 kali lipat",
  "メモリー再生成回数増加": "Peningkatan jumlah pembuatan ulang Memory",
  "メモリー効果": "Efek Memory",
  "メモリー生成完了": "Pembuatan Memory Selesai",
  "メモリー生成時に通信エラーになる現象のお詫びです": "Maaf atas kendala galat komunikasi saat proses pembuatan Memory.",
  "メモリー確定": "Konfirm Memory",
  "メンテナンス中": "Sedang maintenance",
  "メンテナンス完了までもうしばらくお待ちください\nご協力のほどよろしくお願いいたします": "Mohon tunggu sampai maintenance selesai.\nTerima kasih atas kerja samanya.",
  "メンテナンス時間（予定）": "Waktu maintenance (Jadwal)",
  "メンバーが存在しません": "Tidak ada member",
  "メンバー除名": "Keluarkan member",
  "ヨガ": "Yoga",
  "ライバルとパフォーマンスで対決します\n3位以内で試験合格となります": "Bertanding performa dengan rival.\nLulus ujian jika menempati peringkat 3 besar.",
  "ライブツアーイベント 名古屋編": "Event Live Tour - Bagian Nagoya",
  "ライブツアーイベント 大阪編": "Event Live Tour - Bagian Osaka",
  "ライブツアーイベント 広島編": "Event Live Tour - Bagian Hiroshima",
  "ライブ中は最大２０回撮影ができます\nアイドルの姿を記録にのこしましょう！": "Anda dapat mengambil foto hingga 20 kali selama konser.\nAbadikan momen berharga idol Anda!",
  "ラベル": "Label",
  "ランダムな強化済みスキルカード（SSR）を、手札に○〆生成": "Buat Skill Card (SSR) yang ditingkatkan secara acak ke tangan ○〆",
  "ランダムな所持している基本とつくスキルカードを異なるスキルカードにチェンジ": "Ubah satu Skill Card Dasar yang dimiliki menjadi Skill Card lain secara acak",
  "リクエストはありません": "Tidak ada permintaan",
  "リクエスト期間": "Periode Permintaan",
  "リスト更新：": "Pembaruan Daftar:",
  "リズムレイン": "Rhythm Rain",
  "リハーサルを開始する": "Mulai Gladi Resik",
  "リハーサル結果": "Hasil Gladi Resik",
  "リハーサル開始\n": "Gladi Resik Dimulai\n",
  "リリース記念特別パック": "Paket Spesial Perayaan Rilis",
  "リワード名": "Nama Reward",
  "リーダーからのメッセージに\nスタンプでリアクションします": "Berikan reaksi pada pesan leader menggunakan stempel",
  "リーダー交代": "Ganti Leader",
  "レッスンしなきゃ！": "Harus latihan!",
  "レッスンでは、決まったターン数\n行動をすることができます\n今回は残り３ターンみたいですね！": "Dalam Lesson, Anda dapat melakukan aksi dalam jumlah Turn tertentu.\nSepertinya kali ini tersisa 3 Turn lagi!",
  "レッスンと同じスキルカードを使用し、\nスコアを上昇させて順位を競います": "Gunakan Skill Card yang sama dengan saat Lesson untuk meningkatkan Score dan bersaing dalam peringkat.",
  "レッスンの時より\r\nスコアが上昇しましたね！": "Score meningkat lebih tinggi daripada saat Lesson!",
  "レッスンの残りターンが増加": "Jumlah sisa Turn dalam Lesson meningkat",
  "レッスンクリアおめでとう！\nレッスンの目標を達成すると\n報酬を獲得することができますよ": "Selamat telah menyelesaikan Lesson!\nAnda akan mendapatkan hadiah jika berhasil mencapai target Lesson.",
  "レッスンサポート": "Dukungan Lesson",
  "レッスンサポート :": "Dukungan Lesson:",
  "レッスンチケット": "Tiket Lesson",
  "レッスン未CLEARの場合○〆消費体力増加<nobr>1ターン</nobr>": "Jika Lesson belum selesai, ○〆 konsumsi stamina meningkat selama <nobr>1 Turn</nobr>",
  "レッスン未CLEARの場合体力減少": "Stamina berkurang jika Lesson belum selesai",
  "レッスン終了までスキルカードを強化": "Tingkatkan Skill Card hingga Lesson berakhir",
  "レンタルメモリーがありません": "Tidak ada Rental Memory",
  "ログ確認": "Cek Log",
  "ロジックガシャ（毎月1日 5時00分更新）": "Logic Gacha (Update setiap tanggal 1 pukul 05:00)",
  "ローカルラジオの公開収録": "Rekaman Radio Lokal",
  "ー括受取": "Ambil Semua",
  "一同": "Semuanya",
  "一本満足バー": "Ippon Manzoku Bar",
  "一気にスコアを伸ばして3位以上を\n目指しましょう！": "Ayo tingkatkan Score sekaligus dan raih peringkat 3 besar!",
  "一部の字幕を表示": "Tampilkan Sebagian Subtitel",
  "一部レッスンの意図しないトラブル発動条件のお詫びです": "Kompensasi atas kendala syarat pemicu Trouble pada beberapa Lesson.",
  "上手に使っていきましょうね！": "Ayo gunakan dengan bijak!",
  "中間試験の審査基準": "Kriteria Penilaian Ujian Tengah Semester",
  "中間試験まで": "Sisa waktu hingga Ujian Tengah Semester",
  "中間試験クリア時に獲得": "Didapatkan saat menyelesaikan Ujian Tengah Semester",
  "予定の効果はありません": "Tidak ada efek yang dijadwalkan",
  "事": "Tugas",
  "交換Pt、交換内容はガシャごとに異なります。\n獲得済みプロデュースアイドルは「アイドルのピース」に変換されます。": "Poin Penukaran dan konten berbeda untuk setiap Gacha.\nProduce Idol yang sudah dimiliki akan diubah menjadi 'Idol Piece'.",
  "交換あとNN日": "Penukaran berakhir dalam NN hari",
  "交換済": "Sudah Ditukar",
  "今シーズン": "Musim Ini",
  "仕": "Pekerjaan",
  "他のアイドルとスコアを競い合い\n３位以内に入ると合格できます。": "Bersaing Score dengan idol lain.\nAnda akan lulus jika berhasil masuk peringkat 3 besar.",
  "以下のユーザーからアイテムを受け取りました": "Menerima item dari pengguna berikut",
  "以後表示しない": "Jangan tampilkan lagi",
  "以降、ターン終了時、スコア": "Setelah itu, tambah Score di setiap akhir Turn",
  "以降、ターン開始時、スキルカードを引く": "Setelah itu, tarik Skill Card di setiap awal Turn",
  "仲良し？三人組の日常": "Sahabat? Keseharian Tiga Sekawan",
  "件のアイテムを獲得しました": "Item telah didapatkan",
  "休みました": "Beristirahat",
  "体": "Tubuh",
  "余剰分のみ": "Hanya bagian berlebih",
  "使用不可など、レッスンの邪魔になるスキルカード": "Skill Card yang menghambat Lesson, seperti yang tidak bisa digunakan",
  "保存して中断": "Simpan dan Berhenti Sejenak",
  "倉本千奈誕生日記念のプレゼントです": "Hadiah perayaan ulang tahun China Kuramoto.",
  "元": "Asal",
  "元気に": "Dengan Bersemangat",
  "先のアチーブメント": "Achievement Sebelumnya",
  "入手時強化": "Tingkatkan saat didapatkan",
  "全てのミッションをクリアしました": "Semua misi telah diselesaikan",
  "全ての字幕を表示": "Tampilkan Semua Subtitel",
  "全パネルミッションクリア": "Semua Panel Mission Selesai",
  "全ミッションクリアで獲得": "Didapatkan dengan menyelesaikan semua misi",
  "全ミッションクリア報酬": "Hadiah penyelesaian semua misi",
  "再タップで\n選択": "Ketuk lagi untuk\nmemilih",
  "再タップで\n選択解除": "Ketuk lagi untuk\nbatal memilih",
  "再挑戦アイテム": "Item Mengulang Kembali",
  "再生成1回目": "Pembuatan ulang pertama",
  "分スコア上昇": "Peningkatan Score per menit",
  "初回報酬": "Hadiah Pertama Kali",
  "初心者パック\n＋おまけ付き": "Paket Pemula\n+ Bonus Tambahan",
  "初星\nアチーブ": "Hatsuboshi\nAchievement",
  "初星コミュイベントで解放": "Terbuka melalui Event Commu Hatsuboshi",
  "初星プロデュース": "Hatsuboshi Produce",
  "初星学園 ボクシング科。篠澤 広選手のデビュー戦1ラウンド目に放たれたKOの瞬間の一枚。": "Departemen Tinju Akademi Hatsuboshi. Sebuah foto momen KO pada ronde pertama dalam pertandingan debut atlet Hiro Shinosawa.",
  "初星学園オープンキャンパス記念&事前登録のプレゼントです": "Hadiah pendaftaran awal dan perayaan Open Campus Akademi Hatsuboshi.",
  "初星学園課題60達成で解放": "Terbuka setelah menyelesaikan Tugas 60 Akademi Hatsuboshi",
  "初星課題初": "Tugas Pertama Hatsuboshi",
  "別の端末でログインされたか、アクセストークンの有効期限が切れたため、タイトルへ戻ります。": "Anda telah masuk di perangkat lain atau masa berlaku akses telah habis. Kembali ke halaman judul.",
  "利用規約、プライバシーポリシーおよびグローバルコンセントに同意してから本サービスをご利用ください。\nまた、未成年の方は、法定代理人（ご両親等）の同意が必要です。\n\n※ないようがわからないときは\nおうちのひとにがめんをみせてください。": "Harap setujui Syarat Layanan, Kebijakan Privasi, dan Persetujuan Global sebelum menggunakan layanan ini.\nBagi pengguna di bawah umur, diperlukan persetujuan dari wali hukum (orang tua, dsb).\n\n※Jika tidak memahami isinya,\nharap tunjukkan layar ini kepada orang dewasa di rumah.",
  "加入申請がありません": "Tidak ada pengajuan bergabung",
  "効果内容と発動条件を確認して\nしっかり対策しましょう！": "Periksa detail efek serta syarat pemicunya,\ndan pastikan untuk bersiap dengan matang!",
  "勝利Pt": "Poin Kemenangan",
  "募集するアイテムを１つ選んでください": "Silakan pilih satu item untuk diminta",
  "友達招待のコード入力で獲得した報酬です": "Hadiah yang didapatkan dari memasukkan kode undangan teman.",
  "受け取りが完了しました。": "Penerimaan telah selesai.",
  "受け取り期限：": "Batas waktu pengambilan:",
  "受け取るPアイテムを一つ選んでください": "Silakan pilih satu P-Item untuk diambil",
  "合格目標達成": "Target kelulusan tercapai",
  "合計ファン数を3,000,000人にしよう": "Ayo raih total 3.000.000 penggemar",
  "合計獲得スコア": "Total Perolehan Score",
  "名前": "Nama",
  "名前を繰り返す": "Ulangi Nama",
  "商店街で街興し": "Revitalisasi Kawasan Perbelanjaan",
  "営業先を選択してください": "Silakan pilih lokasi kerja",
  "固定": "Tetap",
  "固有Pカード強化": "Peningkatan P-Card Unik",
  "報酬リスト\n": "Daftar Hadiah\n",
  "報酬未受け取り": "Hadiah belum diambil",
  "変更\n": "Ubah\n",
  "大きくスコアをのばすことができる\nスキルカードを\n積極的に使っていきましょう": "Mari aktif gunakan Skill Card yang dapat\nmeningkatkan Score Anda\nsecara signifikan!",
  "大成功確定\n報酬1.5倍": "Jaminan Sukses Besar\nHadiah 1,5 Kali Lipat",
  "大運動会に向けて自主練だ！": "Latihan mandiri untuk Festival Olahraga Besar!",
  "天使の微笑み": "Senyuman Malaikat",
  "好印象を増加するスキルカード": "Skill Card peningkat Good Impression",
  "好調を増加するスキルカード": "Skill Card peningkat Good Shape",
  "子どもと体操教室": "Kelas Senam bersama Anak-anak",
  "実": "Ya",
  "実績": "Achievement",
  "対戦詳細": "Detail Pertandingan",
  "小見出し": "Subjudul",
  "強化確認": "Konfirmasi Peningkatan",
  "強気に変更するスキルカード": "Skill Card untuk mengubah status menjadi Confident",
  "後、体力回復": "Setelah itu, pulihkan stamina",
  "必要ファン投票数": "Jumlah fan-votes yang dibutuhkan",
  "応援/\nトラブル": "Dukungan/\nTrouble",
  "応用研修": "Pelatihan Lanjutan",
  "成功で": "Jika sukses",
  "所持一覧": "Daftar Milik",
  "撮影TOP": "Menu Utama Foto",
  "新アイテム『メモリー再生成チケット』追加のプレゼントです": "Hadiah item baru 'Tiket Pembuatan Ulang Memory' telah ditambahkan.",
  "昇級ライン": "Batas Kenaikan Peringkat",
  "普": "Umum",
  "最初にプロデュースする\nアイドルを選択してください": "Silakan pilih idol yang ingin Anda\nProduce pertama kali",
  "最大までLv強化されています": "Level telah ditingkatkan hingga maksimal",
  "最後にもう１枚選択してみましょう！": "Ayo pilih satu kartu lagi untuk terakhir kalinya!",
  "最終オーディションに合格する": "Lulus Audisi Final",
  "最終試験\n1位": "Ujian Final\nPeringkat 1",
  "最終試験で不合格": "Gagal dalam Ujian Final",
  "最終試験の審査基準": "Kriteria Penilaian Ujian Final",
  "最終試験まで": "Hingga Ujian Final",
  "最高評価点": "Poin Evaluasi Tertinggi",
  "月村 手毬の親愛度Lvを10にする": "Tingkatkan Level Kedekatan Temari Tsukimura hingga Level 10",
  "月村手毬誕生日記念のプレゼントです": "Hadiah perayaan ulang tahun Temari Tsukimura.",
  "未入手にの楽曲再生はショートverになります": "Lagu yang belum didapatkan akan diputar dalam versi pendek",
  "未成年の方が有料コンテンツを購入する場合は、 \n必ず法定代理人（ご両親等）の同意を得てから\n購入してください。": "Jika pengguna di bawah umur ingin membeli konten berbayar,\npastikan untuk mendapatkan persetujuan dari\nwali hukum (orang tua, dsb) sebelum membeli.",
  "未成年の方へ": "Untuk pengguna di bawah umur",
  "本日の挑戦権を消費しました": "Kesempatan tantangan hari ini telah digunakan",
  "本日レンタル可能回数 0/0": "Kesempatan sewa hari ini: 0/0",
  "本日残り0回": "Sisa hari ini: 0x",
  "本日無料あと1回": "Gratis 1x lagi hari ini",
  "本来消費する体力より少ない体力消費で\nスキルカードが使えましたね": "Anda berhasil menggunakan Skill Card dengan konsumsi stamina yang lebih sedikit dari biasanya.",
  "条件1.": "Syarat 1.",
  "条件を満たすごとに、レッスン終了まで、このスキルカード自身の性能が変化する": "Setiap kali syarat terpenuhi, performa Skill Card ini akan berubah hingga Lesson berakhir",
  "条件：ボーカル100位以上": "Syarat: Peringkat Vocal 100 atau lebih",
  "条件：ボーカル100位以上\n2行目": "Syarat: Peringkat Vocal 100 atau lebih\nBaris ke-2",
  "東京某所の「初星学園」に在籍する\nアイドル候補生たちが、一人前のアイドルへと\n成長していく物語": "Kisah perjuangan para kandidat idol di\n[Akademi Hatsuboshi] yang berlokasi di Tokyo\nuntuk menjadi idol yang sesungguhnya",
  "枚減少 <color=#FF3381>2 turns</color>": "Berkurang <color=#FF3381>2 Turn</color>",
  "某学園出向者": "Utusan dari Akademi Tertentu",
  "森林浴スポット": "Spot Terapi Hutan",
  "次": "Lanjut",
  "次のターン": "Lanjutkan Turn",
  "次のランクまで100": "100 lagi ke peringkat berikutnya",
  "次の選択肢まで": "Hingga pilihan berikutnya",
  "次シーズン情報": "Informasi musim berikutnya",
  "残り": "Sisa",
  "残りターン": "Sisa Turn",
  "残りターン数": "Jumlah Sisa Turn",
  "毎月更新プレミアムパス": "Pass Premium Bulanan",
  "水族館のナビゲーション": "Navigasi Akuarium",
  "活動支給選択時、ボーカル上昇+": "Saat memilih dukungan kegiatan, kenaikan Vocal +",
  "活動費で合計1,500,000のマニーを受け取ろう": "Dapatkan total 1.500.000 Money dari Biaya Kegiatan",
  "派手な動きと一緒に": "Bersamaan dengan gerakan mencolok",
  "消費体力が大きいスキルカードほど\n体力の消費量を減少する値が\n大きくなります": "Semakin besar konsumsi stamina sebuah Skill Card,\nsemakin besar pula nilai pengurangan\nkonsumsi staminanya.",
  "温存に変更するスキルカード": "Skill Card untuk mengubah status menjadi Preservation",
  "温泉": "Pemandian Air Panas",
  "獲得Pポイント": "Perolehan P-Poin",
  "獲得できる〇〇(※デイリー/ウィークリー)ptが最大に達しました": "Poin 〇〇 (Harian/Mingguan) yang bisa didapatkan telah mencapai batas maksimal.",
  "獲得アイテムはありません": "Tidak ada item yang didapatkan",
  "獲得可能なスキルカードの候補を再抽選しますか？\n<color=#FF5F5F>プロデュース中の再抽選可能回数には制限があります</color>": "Apakah Anda ingin memilih ulang kandidat Skill Card yang bisa didapatkan?\n<color=#FF5F5F>Jumlah pemilihan ulang selama Produce terbatas.</color>",
  "獲得済みのプロデュースアイドルは「アイドルのピース」に変換されます。": "Produce Idol yang sudah dimiliki akan diubah menjadi 'Idol Piece'.",
  "現在12ターン目": "Sekarang Turn ke-12",
  "現在1ターン目": "Sekarang Turn ke-1",
  "現在、おすすめ商品はありません": "Saat ini tidak ada produk rekomendasi",
  "現在のターン": "Turn Saat Ini",
  "申請拒否": "Tolak Pengajuan",
  "異なるスキルカードにチェンジするやつ": "Sesuatu yang mengubah kartu menjadi Skill Card lain",
  "発動中のアビリティはありません": "Tidak ada kemampuan yang aktif",
  "発動中の効果なし": "Tidak ada efek yang aktif",
  "白線 '24夏": "Garis Putih '24 Musim Panas",
  "相談の全項目割増": "Semua Item Konsultasi Meningkat",
  "私たちの今後の方針について、\n重要な話があるの。": "Ada hal penting yang ingin aku bicarakan\nmengenai rencana kita ke depannya.",
  "秦谷美鈴の「NEXT IDOL AUDITION」追加準備中": "Sedang menyiapkan penambahan \"NIA\" Misuzu Hataya",
  "第1話を読了で解放": "Terbuka setelah membaca Episode 1",
  "素材を消費して指定段階まで特訓を行いますか？": "Gunakan material untuk melakukan Latihan Khusus hingga tahap yang ditentukan?",
  "終了まで30日": "30 Hari Hingga Berakhir",
  "終了時刻 :": "Waktu Berakhir :",
  "終了間近の\nイベントあり": "Ada Event yang\nsegera berakhir",
  "絶好調を増加するスキルカード": "Skill Card peningkat Excellent Shape",
  "総合ランキング": "Semua Peringkat",
  "編成可能なメモリーがありません。": "Tidak ada Memory yang dapat disusun.",
  "編成確認": "Konfirm Susunan",
  "縦画面に戻ります": "Kembali ke mode potret",
  "育成したパラメータによって、\nそのターンのスキルカードに\nかかる倍率が変わります": "Pengganda pada Skill Card Turn tersebut akan berubah tergantung pada Parameter yang ditingkatkan.",
  "背景名": "Nama Latar Belakang",
  "脂質": "Lemak",
  "脱出ゲーム": "Game Melarikan Diri",
  "自動でメモリーを編成します\n<color=#FF5F5F>※現在の編成は保存されません</color>": "Memory akan disusun secara otomatis.\n<color=#FF5F5F>※Susunan saat ini tidak akan disimpan.</color>",
  "花海佑芽登場記念のプレゼントです": "Hadiah perayaan kemunculan Ume Hanami.",
  "落ちこぼれからの挑戦\n倉本 千奈のプロデュースを10回完了": "Tantangan Siswa Terpuruk:\nSelesaikan Produce China Kuramoto sebanyak 10 kali.",
  "葛城リーリヤ誕生日記念のプレゼントです": "Hadiah perayaan ulang tahun Lilja Katsuragi.",
  "藤崎ことね": "Kotone Fujita",
  "血液型": "Golongan Darah",
  "衣装・付き!": "Termasuk Kostum!",
  "親密度0/10": "Bond 0/10",
  "親愛度 10/10": "Bond 10/10",
  "親愛度7以上にする": "Tingkatkan Bond hingga 7 keatas",
  "親愛度Lv2の解放条件": "Syarat pembukaan Bond Level 2",
  "親愛度コミュ 第2話": "Bond Commu Episode 2",
  "親愛度コミュグループ": "Grup Bond Commu",
  "親愛度コミュブループ": "Grup Bond Commu",
  "親愛度コミュ及び初星コミュにおいて、設定された速度でテキストが表示されます。": "Dalam Bond Commu dan Hatsuboshi Commu, teks akan ditampilkan sesuai kecepatan yang diatur.",
  "解除予定時刻：YYYY/MM/DD hh:mm:ss": "Jadwal Berakhir: YYYY/MM/DD hh:mm:ss",
  "許可": "Izin",
  "試験・ステージの残りターンが増加": "Jumlah sisa Turn dalam Ujian/Panggung meningkat",
  "試験中1回": "1x selama ujian",
  "試験中強化": "Tingkatkan selama ujian",
  "試験終了までスキルカードを強化": "Tingkatkan Skill Card hingga Ujian berakhir",
  "試験終了時、\n３位以内だと合格になりますよ": "Anda akan lulus jika menempati peringkat 3 besar\nsaat Ujian berakhir.",
  "試験終了時、体力回復": "Pulihkan stamina saat Ujian berakhir",
  "購入可能回数": "Jumlah Pembelian: ",
  "購入期限": "Batas Waktu Pembelian",
  "購入済み": "Sudah Dibeli",
  "趣味": "Hobi",
  "追い込み": "Latihan Akhir",
  "追い込み\nボーナス": "Bonus\nLatihan Akhir",
  "追い込みボーナス": "Bonus Latihan Akhir",
  "通信エラーです": "Terjadi galat komunikasi",
  "連携ミッションの進め方": "Cara Menyelesaikan Misi Terhubung",
  "遊園地のステージ": "Panggung Taman Hiburan",
  "選択したフォトでメモリー生成を行いますか？": "Buat Memory menggunakan foto yang dipilih?",
  "選択枠メニューはありません": "Tidak ada menu pilihan",
  "重複\n": "Duplikat\n",
  "開始時刻 :": "Waktu Mulai :",
  "除名": "Keluarkan",
  "集中が1増加するごとに、パラメータ上昇量を1増加": "Setiap kenaikan 1 poin Focus, jumlah peningkatan Parameter bertambah 1",
  "集中を増加するスキルカード": "Skill Card peningkat Focus"
}
